COPYING
ilias_course_watcher/CourseWatcher.py
ilias_course_watcher/__init__.py
ilias_course_watcher-0.1.2.dist-info/entry_points.txt
ilias_course_watcher-0.1.2.dist-info/COPYING
ilias_course_watcher-0.1.2.dist-info/WHEEL
ilias_course_watcher-0.1.2.dist-info/METADATA
ilias_course_watcher-0.1.2.dist-info/RECORD
