Metadata-Version: 2.1
Name: ilias-course-watcher
Version: 0.1.2
Summary: Periodically check if courses are available
Home-page: https://gitlab.com/dann-merlin/ilias-course-watcher
License: GPLv3
Author: Merlin Sievers
Author-email: merlin@sievers.dev
Requires-Python: >=3.9,<4.0
Classifier: License :: OSI Approved :: GNU General Public License v3 (GPLv3)
Classifier: License :: Other/Proprietary License
Classifier: Programming Language :: Python :: 3
Classifier: Programming Language :: Python :: 3.10
Classifier: Programming Language :: Python :: 3.9
Requires-Dist: beautifulsoup4 (>=4.11.1,<5.0.0)
Requires-Dist: pyxdg (>=0.28,<0.29)
Requires-Dist: requests (>=2.28.1,<3.0.0)
Project-URL: Repository, https://gitlab.com/dann-merlin/ilias-course-watcher
